ordered_hash_set.py
ordered_hash_set-0.1.3.dist-info/LICENSE.txt
ordered_hash_set-0.1.3.dist-info/METADATA
ordered_hash_set-0.1.3.dist-info/WHEEL
ordered_hash_set-0.1.3.dist-info/top_level.txt
ordered_hash_set-0.1.3.dist-info/RECORD
